nbp.py
nbp_cli-0.1.2.dist-info/licenses/LICENSE
nbp_cli-0.1.2.dist-info/METADATA
nbp_cli-0.1.2.dist-info/WHEEL
nbp_cli-0.1.2.dist-info/entry_points.txt
nbp_cli-0.1.2.dist-info/top_level.txt
nbp_cli-0.1.2.dist-info/RECORD
