Metadata-Version: 2.4
Name: nbp-cli
Version: 0.1.2
Summary: Nano Banana Pro - CLI for Gemini image generation
Author: Yishen Tu
License-Expression: MIT
Project-URL: Repository, https://github.com/YishenTu/nbp-cli
Keywords: nanobanana-pro,gemini,image-generation,cli,ai,google
Requires-Python: >=3.12
License-File: LICENSE
Requires-Dist: google-genai>=1.56.0
Requires-Dist: pillow>=12.0.0
Requires-Dist: python-dotenv>=1.2.1
Dynamic: license-file
